pycrossword/__init__.py
pycrossword/__main__.py
pycrossword/_logger.py
pycrossword/_utils.py
pycrossword/clue/__init__.py
pycrossword/clue/clue.py
pycrossword/crossword/__init__.py
pycrossword/crossword/utils.py
pycrossword/crossword/_v2/__init__.py
pycrossword/crossword/_v2/generator.py
pycrossword/word/__init__.py
pycrossword/word/word.py
pycrossword_generator-0.3.0.dist-info/LICENSE
pycrossword_generator-0.3.0.dist-info/METADATA
pycrossword_generator-0.3.0.dist-info/WHEEL
pycrossword_generator-0.3.0.dist-info/entry_points.txt
pycrossword_generator-0.3.0.dist-info/top_level.txt
pycrossword_generator-0.3.0.dist-info/RECORD
