Metadata-Version: 2.1
Name: pycrossword-generator
Version: 0.3.0
Summary: A Python library and CLI tool for generating customizable crossword puzzles.
Author-email: Vladyslav Novotnyi <psejjkuczo@proxiedmail.com>
Maintainer-email: Vladyslav Novotnyi <psejjkuczo@proxiedmail.com>
License: The MIT License (MIT)
Project-URL: Homepage, https://github.com/fabelx/pycrossword
Project-URL: Bug Reports, https://github.com/fabelx/pycrossword/issues
Project-URL: Source, https://github.com/fabelx/pycrossword
Keywords: crossword,generator,puzzle
Classifier: Development Status :: 4 - Beta
Classifier: Intended Audience :: End Users/Desktop
Classifier: License :: OSI Approved :: MIT License
Classifier: Operating System :: OS Independent
Classifier: Programming Language :: Python :: 3
Classifier: Programming Language :: Python :: 3.12
Classifier: Programming Language :: Python :: 3.13
Classifier: Programming Language :: Python :: 3 :: Only
Requires-Python: >=3.12
License-File: LICENSE
Requires-Dist: openai >=1.25.0
Provides-Extra: dev
Requires-Dist: build ; extra == 'dev'
Provides-Extra: lint
Requires-Dist: black ==24.4.2 ; extra == 'lint'
Requires-Dist: isort ==5.13.2 ; extra == 'lint'
Provides-Extra: test
Requires-Dist: coverage ; extra == 'test'
Requires-Dist: pytest ; extra == 'test'
Requires-Dist: pytest-cov ; extra == 'test'
